envidat/__init__.py
envidat/api/__init__.py
envidat/api/v1.py
envidat/config/config_converters.json
envidat/converters/__init__.py
envidat/converters/bibtex_converter.py
envidat/converters/datacite_converter.py
envidat/converters/dcat_ap_converter.py
envidat/converters/dif_converter.py
envidat/converters/iso_converter.py
envidat/converters/ris_converter.py
envidat/converters/xml_converter.py
envidat/doi/__init__.py
envidat/doi/datacite_publisher.py
envidat/doi/datacite_updater.py
envidat/metadata.py
envidat/s3/__init__.py
envidat/s3/bucket.py
envidat/s3/exceptions.py
envidat/utils.py
envidat_utils-1.4.13.dist-info/WHEEL
envidat_utils-1.4.13.dist-info/METADATA
envidat_utils-1.4.13.dist-info/licenses/LICENCE
envidat_utils-1.4.13.dist-info/RECORD
