Metadata-Version: 2.1
Name: envidat-utils
Version: 1.4.13
Summary: Utilities in Python for the WSL EnviDat project.
License: MIT
Keywords: envidat,s3,ckan,wsl
Author-email: Sam Woodcock <samuel.woodcock@wsl.ch>,Rebecca Kurup Buchholz <rebecca.kurup@wsl.ch>,Ranita Pal <ranita.pal@wsl.ch>
Requires-Python: >=3.9
Classifier: Programming Language :: Python :: 3
Classifier: Programming Language :: Python :: 3.10
Classifier: Topic :: Utilities
Requires-Dist: boto3>=1.22.12
Requires-Dist: jsonschema>=4.17.3
Requires-Dist: requests>=2.27.1
Requires-Dist: validators>=0.20.0
Requires-Dist: xmltodict>=0.13.0
Provides-Extra: dotenv
Requires-Dist: python-dotenv>=1.0.0; extra == "dotenv"
Project-URL: documentation, https://envidat.gitlab-pages.wsl.ch/envidat-python-utils
Project-URL: homepage, https://www.envidat.ch
Project-URL: repository, https://gitlabext.wsl.ch/EnviDat/envidat-python-utils.git
